colette/__init__.py
colette/__main__.py
colette/email/__init__.py
colette/email/base.py
colette/email/mail_macos.py
colette/email/outlook_macos.py
colette/email/outlook_windows.py
colette/email/smtp.py
colette/models.py
colette/solver.py
colette/storage.py
colette-0.2.4.dist-info/LICENSE
colette-0.2.4.dist-info/METADATA
colette-0.2.4.dist-info/WHEEL
colette-0.2.4.dist-info/entry_points.txt
colette-0.2.4.dist-info/RECORD
