Metadata-Version: 2.3
Name: colette
Version: 0.2.4
Summary: Manage rounds of coffee roulette
License: AGPL3
Author: David Horsley
Author-email: david.e.horsley@gmail.com
Requires-Python: >=3.10,<4.0
Classifier: License :: Other/Proprietary License
Classifier: Programming Language :: Python :: 3
Classifier: Programming Language :: Python :: 3.10
Classifier: Programming Language :: Python :: 3.11
Classifier: Programming Language :: Python :: 3.12
Classifier: Programming Language :: Python :: 3.13
Requires-Dist: Jinja2 (>=3.1,<4.0)
Requires-Dist: appscript (>=1.2.2,<2.0.0) ; sys_platform == "darwin"
Requires-Dist: mip (>=1.13,<2.0)
Requires-Dist: pywin32 (>=306,<307) ; sys_platform == "win32"
Requires-Dist: tomlkit (>=0.12.1,<0.13.0)
Project-URL: Homepage, https://github.com/dehorsley/colette
Project-URL: Repository, https://github.com/dehorsley/colette.git
